bbb_pru_adc/__init__.py
bbb_pru_adc/capture.py
bbb_pru_adc/driver.py
bbb_pru_adc/main.py
bbb_pru_adc/resources/am335x-pru0.fw
bbb_pru_adc/resources/libdriver.so
bbb_pru_adc-1.3.1.data/data/src/common.h
bbb_pru_adc-1.3.1.data/data/src/driver.c
bbb_pru_adc-1.3.1.data/data/src/driver.h
bbb_pru_adc-1.3.1.data/data/src/firmware.c
bbb_pru_adc-1.3.1.data/data/src/firmware.cmd
bbb_pru_adc-1.3.1.data/data/src/firmware_resource_table.h
bbb_pru_adc-1.3.1.dist-info/LICENSE
bbb_pru_adc-1.3.1.dist-info/METADATA
bbb_pru_adc-1.3.1.dist-info/WHEEL
bbb_pru_adc-1.3.1.dist-info/top_level.txt
bbb_pru_adc-1.3.1.dist-info/RECORD
