Metadata-Version: 2.1
Name: bbb-pru-adc
Version: 1.3.1
Summary: Streaming capture of ADC on BeagleBone (Black)
Home-page: https://github.com/pgmmpk/bbb_pru_adc
Author: Mike Kroutikov
Author-email: pgmmpk@gmail.com
License: UNKNOWN
Keywords: beaglebone black adc pru
Platform: UNKNOWN
Classifier: Development Status :: 4 - Beta
Classifier: Intended Audience :: Developers
Classifier: License :: OSI Approved :: MIT License
Classifier: Programming Language :: Python :: 3
Classifier: Programming Language :: Python :: 3.5
Classifier: Programming Language :: Python :: 3.6
Classifier: Programming Language :: Python :: 3.7
Classifier: Programming Language :: Python :: 3.8
Requires-Python: >=3.5, <4
